keyscraper/__init__.py
keyscraper/dynamicscraper.py
keyscraper/staticscraper.py
keyscraper/utils.py
keyscraper-1.1.4.dist-info/LICENSE
keyscraper-1.1.4.dist-info/METADATA
keyscraper-1.1.4.dist-info/WHEEL
keyscraper-1.1.4.dist-info/top_level.txt
keyscraper-1.1.4.dist-info/RECORD
