Metadata-Version: 2.1
Name: keyscraper
Version: 1.1.4
Summary: A library for web scraping.
Home-page: https://github.com/keyywind/keyscraper
Author: keyywind
Author-email: kevinwater127@gmail.com
License: UNKNOWN
Project-URL: Bug Tracker, https://github.com/keyywind/keyscraper/issues
Platform: UNKNOWN
Classifier: Programming Language :: Python :: 3
Classifier: License :: OSI Approved :: MIT License
Classifier: Operating System :: OS Independent
Requires-Python: >=3.6
License-File: LICENSE
Requires-Dist: markdown
Requires-Dist: requests
Requires-Dist: selenium
Requires-Dist: pandas
Requires-Dist: lxml
Requires-Dist: bs4
